scheduler/ProcessTask.py
scheduler/Scheduler.py
scheduler/Task.py
scheduler/ThreadTask.py
scheduler/__init__.py
scheduler/utils.py
AsyncProcessScheduler-0.9.0b1.dist-info/LICENSE
AsyncProcessScheduler-0.9.0b1.dist-info/METADATA
AsyncProcessScheduler-0.9.0b1.dist-info/WHEEL
AsyncProcessScheduler-0.9.0b1.dist-info/top_level.txt
AsyncProcessScheduler-0.9.0b1.dist-info/RECORD
