Metadata-Version: 2.1
Name: AsyncProcessScheduler
Version: 0.9.0b1
Summary: GUI-friendly library for scheduling processes using coroutines.
Home-page: https://github.com/CabbageDevelopment/async-process-scheduler
Author: Sam McCormack
Author-email: contact@cabbagedevelopment.com
License: UNKNOWN
Project-URL: Source, https://github.com/CabbageDevelopment/async-process-scheduler
Keywords: async asyncio processing multiprocessing scheduler scheduling processes coroutines gui
Platform: UNKNOWN
Classifier: Development Status :: 4 - Beta
Classifier: Intended Audience :: Developers
Classifier: License :: OSI Approved :: MIT License
Classifier: Programming Language :: Python :: 3.6
Classifier: Programming Language :: Python :: 3.7
Classifier: Programming Language :: Python :: 3.8
Requires-Python: ~=3.6
Requires-Dist: psutil
